libbs/__init__.py
libbs/__main__.py
libbs/configuration.py
libbs/logger.py
libbs/plugin_installer.py
libbs/api/__init__.py
libbs/api/artifact_dict.py
libbs/api/artifact_lifter.py
libbs/api/decompiler_client.py
libbs/api/decompiler_interface.py
libbs/api/decompiler_server.py
libbs/api/type_parser.py
libbs/api/utils.py
libbs/artifacts/__init__.py
libbs/artifacts/artifact.py
libbs/artifacts/comment.py
libbs/artifacts/context.py
libbs/artifacts/decompilation.py
libbs/artifacts/enum.py
libbs/artifacts/formatting.py
libbs/artifacts/func.py
libbs/artifacts/global_variable.py
libbs/artifacts/patch.py
libbs/artifacts/segment.py
libbs/artifacts/stack_variable.py
libbs/artifacts/struct.py
libbs/artifacts/typedef.py
libbs/decompiler_stubs/__init__.py
libbs/decompiler_stubs/ida_libbs.py
libbs/decompiler_stubs/angr_libbs/__init__.py
libbs/decompiler_stubs/binja_libbs/__init__.py
libbs/decompilers/__init__.py
libbs/decompilers/angr/__init__.py
libbs/decompilers/angr/artifact_lifter.py
libbs/decompilers/angr/compat.py
libbs/decompilers/angr/interface.py
libbs/decompilers/binja/__init__.py
libbs/decompilers/binja/artifact_lifter.py
libbs/decompilers/binja/hooks.py
libbs/decompilers/binja/interface.py
libbs/decompilers/ghidra/__init__.py
libbs/decompilers/ghidra/artifact_lifter.py
libbs/decompilers/ghidra/hooks.py
libbs/decompilers/ghidra/interface.py
libbs/decompilers/ghidra/compat/__init__.py
libbs/decompilers/ghidra/compat/headless.py
libbs/decompilers/ghidra/compat/imports.py
libbs/decompilers/ghidra/compat/state.py
libbs/decompilers/ghidra/compat/transaction.py
libbs/decompilers/ida/__init__.py
libbs/decompilers/ida/artifact_lifter.py
libbs/decompilers/ida/compat.py
libbs/decompilers/ida/hooks.py
libbs/decompilers/ida/ida_ui.py
libbs/decompilers/ida/interface.py
libbs/ui/__init__.py
libbs/ui/qt_objects.py
libbs/ui/utils.py
libbs/ui/version.py
libbs-3.3.3.dist-info/licenses/LICENSE
libbs-3.3.3.dist-info/METADATA
libbs-3.3.3.dist-info/WHEEL
libbs-3.3.3.dist-info/entry_points.txt
libbs-3.3.3.dist-info/top_level.txt
libbs-3.3.3.dist-info/RECORD
