Metadata-Version: 2.4
Name: libbs
Version: 3.3.3
Summary: Your Only Decompiler API Lib - A generic API to script in and out of decompilers
License: BSD 2 Clause
Project-URL: Homepage, https://github.com/binsync/libbs
Classifier: License :: OSI Approved :: BSD License
Classifier: Programming Language :: Python :: 3
Classifier: Programming Language :: Python :: 3.10
Classifier: Programming Language :: Python :: 3.12
Requires-Python: >=3.10
License-File: LICENSE
Requires-Dist: toml
Requires-Dist: ply
Requires-Dist: pycparser<3.0
Requires-Dist: setuptools
Requires-Dist: prompt_toolkit
Requires-Dist: tqdm
Requires-Dist: psutil
Requires-Dist: pyghidra
Requires-Dist: platformdirs
Requires-Dist: filelock
Requires-Dist: networkx
Provides-Extra: test
Requires-Dist: pytest; extra == "test"
Requires-Dist: angr; extra == "test"
Requires-Dist: requests; extra == "test"
Requires-Dist: ipdb; extra == "test"
Provides-Extra: ghidra
Requires-Dist: PySide6-Essentials!=6.7.0,>=6.4.2; extra == "ghidra"
Dynamic: license-file
